{
  "Modality": {
    "Interaction_modality": "pad",
    "Size": {
      "width": 768,
      "height": 1024
    }
  },
  "Interface": [
    {
      "title": "Top 20 countries",
      "Encoding": {
        "url": "demo1/table.csv",
        "y": {
          "field": "country",
          "datum": "nominal",
          "sort": "-x"
        },
        "x": {
          "field": "Total cases (M)",
          "datum": "quantitative",
          "scale": {
            "domain": [0,22]
          }
        }
      },
      "ViewType": {
        "type": "bar"
      },
      "BoundingBox": {
        "CenterPosition": {
          "x": 0.0885416,
          "y": 0.5
        },
        "Size": {
          "width": 0.177083,
          "height": 1
        }
      }
    },
    {
      "Encoding":[
        {
          "projection": {
            "type":"mercator"
          },
          "url": "country-110m.json",
          "feature": "countries"
        },
        {
          "url": "demo1/map.csv",
          "x": {
            "field": "Long",
            "datum": "quantitative"
          },
          "y": {
            "field": "Lat",
            "datum": "quantitative"
          },
          "size":{
            "field":"Total cases",
            "datum": "quantitative",
            "legend": {
              "format": "~s"
            }
          }
        }
      ],
      "ViewType": [
        {
          "type": "geoshape",
          "fill": "lightgray",
          "stroke": "white"
        },
        {
          "type": "circle",
          "color": "red"
        }
      ],
      "BoundingBox": {
        "CenterPosition": {
          "x": 0.458333,
          "y": 0.5
        },
        "Size": {
          "width": 0.5625,
          "height": 1
        }
      }
    },
    {
      "Encoding": {
        "url": "demo1/world-covid-data1.csv",
        "x": {
          "field": "date",
          "datum": "temporal",
          "format": "%b"
        },
        "y": {
          "field": "total cases and total deaths (M)",
          "datum": "quantitative",
          "title": null,
          "format": "s"
        },
        "color": {
          "field": "Symbol",
          "datum": "nominal"
        }
      },
      "ViewType": {
        "type": "line"
      },
      "BoundingBox": {
        "CenterPosition": {
          "x": 0.8697916,
          "y": 0.166666
        },
        "Size": {
          "width": 0.260416,
          "height": 0.33333
        }
      }
    },
    {
      "Encoding": {
        "url": "demo1/plot-covid-data.csv",
        "x": {
          "field": "Total cases (lg)",
          "datum": "quantitative"
        },
        "y": {
          "field": "Total deaths (lg)",
          "datum": "quantitative"
        }
      },
      "ViewType": {
        "type": "circle"
      },
      "BoundingBox": {
        "CenterPosition": {
          "x": 0.8697916,
          "y": 0.5
        },
        "Size": {
          "width": 0.260416,
          "height": 0.34
        }
      }
    },
    {
      "Encoding": {
        "url": "demo1/pie-covid-data.csv",
        "theta": {
          "field": "cases",
          "datum": "quantitative"
        },
        "color": {
          "field": "Continent",
          "datum": "nominal"
        }
      },
      "ViewType": {
        "type": "arc"
      },
      "layer": [
        {
          "ViewType": {
            "type": "arc"
          }
        },
        {
          "ViewType": {
            "type": "text"
          },
          "encoding": {
            "text": {
              "field": "percentage",
              "datum": "nominal"
            }
          }
        }
      ],
      "BoundingBox": {
        "CenterPosition": {
          "x": 0.8697916,
          "y": 0.83333
        },
        "Size": {
          "width": 0.260416,
          "height": 0.33333
        }
      }
    }
  ]
}